selectors2.py
selectors2-2.0.1.dist-info/DESCRIPTION.rst
selectors2-2.0.1.dist-info/METADATA
selectors2-2.0.1.dist-info/RECORD
selectors2-2.0.1.dist-info/WHEEL
selectors2-2.0.1.dist-info/metadata.json
selectors2-2.0.1.dist-info/top_level.txt
