Metadata-Version: 1.1
Name: selectors2
Version: 2.0.1
Summary: Back-ported, durable, and portable selectors
Home-page: https://www.github.com/SethMichaelLarson/selectors2
Author: Seth Michael Larson
Author-email: sethmichaellarson@protonmail.com
License: MIT
Keywords: async,file,socket,select,backport
Platform: UNKNOWN
Classifier: Programming Language :: Python :: 2
Classifier: Programming Language :: Python :: 2.6
Classifier: Programming Language :: Python :: 2.7
Classifier: Programming Language :: Python :: 3
Classifier: Programming Language :: Python :: 3.3
Classifier: Programming Language :: Python :: 3.4
Classifier: License :: OSI Approved :: Python Software Foundation License
Classifier: License :: OSI Approved :: MIT License
